apmpython/__init__.py
apmpython/apmpython.py
mw_python_apm-0.1.3.dist-info/LICENSE
mw_python_apm-0.1.3.dist-info/METADATA
mw_python_apm-0.1.3.dist-info/WHEEL
mw_python_apm-0.1.3.dist-info/top_level.txt
mw_python_apm-0.1.3.dist-info/RECORD
