Metadata-Version: 2.1
Name: mw-python-apm
Version: 0.1.3
Summary: This package is use to check the RAM and CPU Usage of Current Device.
Home-page: https://github.com/middleware-labs/agent-apm-python.git
Author: Nidhi_Sharma
License-File: LICENSE
